[ {"key":1,
  "model":"Sirrus P",
  "brand":"Specialized",
  "size": 54,
  "seattube": 485,
  "toptube": 533,
  "headtube": 175,
  "headangle": 72.5,
  "seatangle": 72.25,
  "bbdrop": 64,
  "chainstay": 432,
  "wheelbase": 1023,
  "stack": 575,
  "reach": 388,
  "stemstack":41,
  "stemlength":70,
  "stemangle":-9,
  "spacers":20,
  "bbsaddle":701,
  "saddleheight":725,
  "saddlelength":275,
  "saddlerailstop":40,
  "saddlerailfront":130,
  "saddleraillength":60,
  "bbsetback":31,
  "hbreach":78,
  "hbdrop":125,
  "display":true
 },
 {"key":3,
  "model":"WCB-R-085 P - Yellow",
   "brand":"Workwell",
   "size": 52,
   "seattube": 475,
   "toptube": 529,
   "headtube": 150,
   "headangle": 71.5,
   "seatangle": 74,
   "bbdrop": 72,
   "chainstay": 410,
   "wheelbase": 977,
   "stack": 546,
   "reach": 372,
   "stemstack":40,
   "stemlength":90,
   "stemangle":-6,
     "spacers":30,
       "bbsaddle":701,
       "saddleheight":-1,
         "bbsetback":31,
           "saddlelength":275,
   "saddlerailstop":40,
   "saddlerailfront":130,
   "saddleraillength":60,
         "hbreach":100,
   "hbdrop":125,
   "display":true
  },
 {"key":4,
 "model":"WCB-R-085 S - Red",
  "brand":"Workwell",
  "size": 52,
  "seattube": 475,
  "toptube": 529,
  "headtube": 150,
  "headangle": 71.5,
  "seatangle": 74,
  "bbdrop": 72,
  "chainstay": 410,
  "wheelbase": 977,
  "stack": 546,
  "reach": 372,
  "stemstack":50,
  "stemlength":80,
  "stemangle":-6,
    "spacers":30,
      "bbsaddle":665,
      "saddleheight":-1,
        "bbsetback":0,
          "saddlelength":275,
  "saddlerailstop":40,
  "saddlerailfront":130,
  "saddleraillength":60,
        "hbreach":78,
  "hbdrop":125,
  "display":false
 },
 {"key":22,
 "model":"Sirrus Sport P",
  "brand":"Specialized",
  "size": 52,
  "seattube": 445,
  "toptube": 5130,
  "headtube": 141,
  "headangle": 74.5,
  "seatangle": 76,
  "bbdrop": 63.5,
  "chainstay": 425,
  "wheelbase": 1018,
  "stack": 548.5,
  "reach": 392,
  "stemstack":35,
  "stemlength":65,
  "stemangle":-6,
  "spacers":30,
  "bbsaddle":699,
  "saddleheight":678,
    "saddlelength":275,
  "saddlerailstop":40,
  "saddlerailfront":130,
  "saddleraillength":60,
  "bbsetback":27.5,
    "hbreach":78,
  "hbdrop":125,
  "display":false
 },
 {"key":5,
   "model":"WCB-R-085",
  "brand":"Workwell",
  "size": 54,
  "seattube": 500,
  "toptube": 544,
  "headtube": 165,
  "headangle": 72.5,
  "seatangle": 73.5,
  "bbdrop": 72,
  "chainstay": 410,
  "wheelbase": 982,
  "stack": 567,
  "reach": 377,
    "stemstack":40,
  "stemlength":100,
  "stemangle":-15,
    "spacers":30,
      "bbsaddle":701,
      "saddleheight":-1,
        "bbsetback":31,
          "saddlelength":275,
  "saddlerailstop":40,
  "saddlerailfront":130,
  "saddleraillength":60,
        "hbreach":78,
  "hbdrop":125,
  "display":false
 },
 {"key":44,
   "model":"Fenix SL",
  "brand":"Ridley",
  "size": "S",
  "seattube": 510,
  "toptube": 526,
  "headtube": 142,
  "headangle": 73,
  "seatangle": 73.5,
  "bbdrop": 66,
  "chainstay": 410,
  "wheelbase": 982,
  "stack": 542,
  "reach": 384,
    "stemstack":40,
  "stemlength":100,
  "stemangle":-15,
    "spacers":30,
      "bbsaddle":701,
      "saddleheight":-1,
        "bbsetback":31,
          "saddlelength":275,
  "saddlerailstop":40,
  "saddlerailfront":130,
  "saddleraillength":60,
        "hbreach":78,
  "hbdrop":125,
  "display":false
 },
  {
    "key":5,
    "model":"WCB-R-066",
  "brand":"Workwell",
  "size": 510,
  "seattube": 482,
  "toptube": 531,
  "headtube": 128,
  "headangle": 72.2,
  "seatangle": 73,
  "bbdrop": 68,
  "chainstay": 405,
  "wheelbase": 977,
  "stack": 530,
  "reach": 369,
    "stemstack":40,
  "stemlength":90,
  "stemangle":-9,
    "spacers":30,
      "bbsaddle":701,
        "bbsetback":31,
          "saddlelength":275,
  "saddlerailstop":40,
  "saddlerailfront":130,
  "saddleraillength":60,
        "saddleheight":-1,
        "hbreach":78,
  "hbdrop":125,
  "display":false
 },
 {"key":6,
   "model":"WCB-R-066",
  "brand":"Workwell",
  "size": 540,
  "seattube": 514,
  "toptube": 548,
  "headtube": 148,
  "headangle": 73.1,
  "seatangle": 73,
  "bbdrop": 68,
  "chainstay": 405,
  "wheelbase": 983,
  "stack": 555,
  "reach": 378,
    "stemstack":40,
  "stemlength":100,
  "stemangle":-9,
    "spacers":30,
      "bbsaddle":701,
        "bbsetback":31,
          "saddlelength":275,
  "saddlerailstop":40,
  "saddlerailfront":130,
  "saddleraillength":60,
        "saddleheight":-1,
        "hbreach":78,
  "hbdrop":125,
  "display":false
 },
 {"key":7,
 "model":"Roubaix SL4",
  "brand":"Specialized",
  "size": 52,
  "stack": 547,
  "reach": 379,
  "headtube": 145,
  "headangle": 72,
  "bbdrop": 73,
  "chainstay": 412,
  "wheelbase": 990,
  "toptube": 536,
  "seattube": 475,
  "seatangle": 74,
    "stemstack":40,
  "stemlength":90,
  "stemangle":-7,
    "spacers":30,
      "bbsaddle":701,
        "saddlelength":275,
  "saddlerailstop":40,
  "saddlerailfront":130,
  "saddleraillength":60,
      "saddleheight":-1,
        "bbsetback":31,
        "hbreach":70,
  "hbdrop":125,
  "display":false
 },
 {"key":8,
 "model":"Roubaix SL4",
  "brand":"Specialized",
  "size": 54,
  "stack": 564,
  "reach": 380,
  "headtube": 165,
  "headangle": 72,
  "bbdrop": 71.5,
  "chainstay": 415,
  "wheelbase": 1000,
  "toptube": 547,
  "seattube": 495,
  "seatangle": 73.5,
    "stemstack":40,
  "stemlength":100,
  "stemangle":-7,
    "spacers":30,
      "bbsaddle":701,
        "bbsetback":31,
          "saddlelength":275,
  "saddlerailstop":40,
  "saddlerailfront":130,
  "saddleraillength":60,
        "saddleheight":-1,
        "hbreach":70,
  "hbdrop":125,
  "display":false
 },
 {"key":9,
   "model":"Allez E5 Sport",
  "brand":"Specialized",
  "size": 52,
  "stack": 527,
  "reach": 387,
  "headtube": 120,
  "headangle": 73,
  "bbdrop": 72,
  "chainstay": 407,
  "wheelbase": 974,
  "toptube": 538,
  "seattube": 490,
  "seatangle": 74,
    "stemstack":40,
  "stemlength":90,
  "stemangle":-7,
    "spacers":30,
      "bbsaddle":701,
        "bbsetback":31,
          "saddlelength":275,
  "saddlerailstop":40,
  "saddlerailfront":130,
  "saddleraillength":60,
        "saddleheight":-1,
        "hbreach":70,
  "hbdrop":125,
  "display":false
 },
 {"key":10,
   "model":"Allez E5 Sport",
  "brand":"Specialized",
  "size": 54,
  "stack": 548,
  "reach": 387,
  "headtube": 145,
  "headangle": 73,
  "bbdrop": 69,
  "chainstay": 407,
  "wheelbase": 982,
  "toptube": 549,
  "seattube": 510,
  "seatangle": 73.5,
    "stemstack":40,
  "stemlength":100,
  "stemangle":-7,
    "spacers":30,
      "bbsaddle":701,
        "bbsetback":31,
          "saddlelength":275,
  "saddlerailstop":40,
  "saddlerailfront":130,
  "saddleraillength":60,
        "saddleheight":-1,
        "hbreach":70,
  "hbdrop":125,
  "display":false
 },{"key":21,
  "model":"Sirrus SF",
  "brand":"Specialized",
  "size": 54,
  "seattube": 485,
  "toptube": 533,
  "headtube": 175,
  "headangle": 72.5,
  "seatangle": 72.25,
  "bbdrop": 64,
  "chainstay": 432,
  "wheelbase": 1023,
  "stack": 575,
  "reach": 388,
  "stemstack":41,
  "stemlength":80,
  "stemangle":15,
  "spacers":0,
  "bbsaddle":643,
    "bbsetback":31,
      "saddlelength":275,
  "saddlerailstop":40,
  "saddlerailfront":130,
  "saddleraillength":60,
    "saddleheight":-1,
    "hbreach":0,
  "hbdrop":0,
  "display":false
 },
 {"key":2,
 "model":"Sirrus Sport SF",
  "brand":"Specialized",
  "size": 52,
  "seattube": 445,
  "toptube": 5130,
  "headtube": 141,
  "headangle": 74.5,
  "seatangle": 76,
  "bbdrop": 63.5,
  "chainstay": 425,
  "wheelbase": 1018,
  "stack": 548.5,
  "reach": 392,
  "stemstack":38,
  "stemlength":80,
  "stemangle":15,
  "spacers":30,
  "bbsaddle":643,
    "bbsetback":3,
    "saddleheight":623.5,
      "saddlelength":275,
  "saddlerailstop":40,
  "saddlerailfront":130,
  "saddleraillength":60,
    "hbreach":0,
  "hbdrop":0,
  "display":false
 },
 {"key":23,
 "model":"WCB-R-085 SD",
  "brand":"Workwell",
  "size": 52,
  "seattube": 475,
  "toptube": 529,
  "headtube": 150,
  "headangle": 71.5,
  "seatangle": 74,
  "bbdrop": 72,
  "chainstay": 410,
  "wheelbase": 977,
  "stack": 546,
  "reach": 372,
  "stemstack":40,
  "stemlength":90,
  "stemangle":-15,
  "spacers":30,
  "bbsaddle":661,
    "bbsetback":31,
      "saddlelength":275,
  "saddlerailstop":40,
  "saddlerailfront":130,
  "saddleraillength":60,
    "saddleheight":-1,
    "hbreach":70,
  "hbdrop":122,
  "display":false
 },{"key":41,
  "model":"Sirrus SD",
  "brand":"Specialized",
  "size": 54,
  "seattube": 485,
  "toptube": 533,
  "headtube": 175,
  "headangle": 72.5,
  "seatangle": 72.25,
  "bbdrop": 64,
  "chainstay": 432,
  "wheelbase": 1023,
  "stack": 575,
  "reach": 388,
  "stemstack":41,
  "stemlength":70,
  "stemangle":-35,
  "spacers":20,
  "bbsaddle":661,
    "bbsetback":9,
      "saddlelength":275,
  "saddlerailstop":40,
  "saddlerailfront":130,
  "saddleraillength":60,
    "saddleheight":630,
    "hbreach":70,
  "hbdrop":122,
  "display":false
 },
 {"key":52,
 "model":"Sirrus Sport SD",
  "brand":"Specialized",
  "size": 52,
  "seattube": 445,
  "toptube": 5130,
  "headtube": 141,
  "headangle": 74.5,
  "seatangle": 76,
  "bbdrop": 63.5,
  "chainstay": 425,
  "wheelbase": 1018,
  "stack": 548.5,
  "reach": 392,
  "stemstack":35,
  "stemlength":65,
  "stemangle":-6,
  "spacers":30,
  "bbsaddle":661,
    "saddlelength":275,
  "saddlerailstop":40,
  "saddlerailfront":130,
  "saddleraillength":60,
  "saddleheight":-1,
  "bbsetback":9,
    "hbreach":78,
  "hbdrop":125,
  "display":false
 },
 {"key":53,
 "model":"Avail S",
  "brand":"Liv Giant",
  "size": "S",
  "seattube": 445,
  "toptube": 525,
  "headtube": 150,
  "headangle": 72,
  "seatangle": 74.5,
  "bbdrop": 65,
  "chainstay": 420,
  "wheelbase": 990,
  "stack": 550,
  "reach": 372,
  "stemstack":35,
  "stemlength":90,
  "stemangle":-6,
  "spacers":30,
  "bbsaddle":661,
    "saddlelength":275,
  "saddlerailstop":40,
  "saddlerailfront":130,
  "saddleraillength":60,
  "saddleheight":-1,
  "bbsetback":9,
    "hbreach":70,
  "hbdrop":125,
  "display":false
 },
 {"key":54,
 "model":"Defy P",
  "brand":"Giant",
  "size": "S",
  "seattube": 445,
  "toptube": 530,
  "headtube": 145,
  "headangle": 72,
  "seatangle": 74,
  "bbdrop": 65,
  "chainstay": 420,
  "wheelbase": 990,
  "stack": 545,
  "reach": 373,
  "stemstack":35,
  "stemlength":90,
  "stemangle":-6,
  "spacers":30,
  "bbsaddle":661,
    "saddlelength":275,
  "saddlerailstop":40,
  "saddlerailfront":130,
  "saddleraillength":60,
  "saddleheight":-1,
  "bbsetback":9,
    "hbreach":70,
  "hbdrop":125,
  "display":false
 },
 {"key":55,
 "model":"520 P",
  "brand":"Trek",
  "size": 51,
  "seattube": 482,
  "toptube": 531,
  "headtube": 125,
  "headangle": 70,
  "seatangle": 74,
  "bbdrop": 75,
  "chainstay": 450,
  "wheelbase": 1045,
  "stack": 551,
  "reach": 373,
  "stemstack":35,
  "stemlength":90,
  "stemangle":-6,
  "spacers":30,
  "bbsaddle":661,
    "saddlelength":275,
  "saddlerailstop":40,
  "saddlerailfront":130,
  "saddleraillength":60,
  "saddleheight":-1,
  "bbsetback":9,
    "hbreach":70,
  "hbdrop":125,
  "display":false
 },
 {"key":56,
 "model":"Sutra P",
  "brand":"Kona",
  "size": 48.5,
  "seattube": 485,
  "toptube": 540,
  "headtube": 105,
  "headangle": 71,
  "seatangle": 74,
  "bbdrop": 72,
  "chainstay": 445,
  "wheelbase": 1039,
  "stack": 558,
  "reach": 380,
  "stemstack":35,
  "stemlength":90,
  "stemangle":-6,
  "spacers":30,
  "bbsaddle":661,
    "saddlelength":275,
  "saddlerailstop":40,
  "saddlerailfront":130,
  "saddleraillength":60,
  "saddleheight":-1,
  "bbsetback":9,
    "hbreach":70,
  "hbdrop":125,
  "display":false
 },
 {"key":57,
 "model":"C5 P",
  "brand":"Cervelo",
  "size": 51,
  "seattube": 485,
  "toptube": 531,
  "headtube": 138.3,
  "headangle": 70,
  "seatangle": 73,
  "bbdrop": 77.5,
  "chainstay": 420,
  "wheelbase": 1010,
  "stack": 549,
  "reach": 362,
  "stemstack":35,
  "stemlength":90,
  "stemangle":-6,
  "spacers":30,
  "bbsaddle":700,
    "saddlelength":275,
  "saddlerailstop":40,
  "saddlerailfront":130,
  "saddleraillength":60,
  "saddleheight":-1,
  "bbsetback":9,
    "hbreach":70,
  "hbdrop":125,
  "display":false
 },
 {"key":58,
 "model":"Domane 4.3 P",
  "brand":"Trek",
  "size": 52,
  "seattube": 475,
  "toptube": 530,
  "headtube": 145,
  "headangle": 71.3,
  "seatangle": 74.2,
  "bbdrop": 80,
  "chainstay": 420,
  "wheelbase": 1003,
  "stack": 561,
  "reach": 371,
  "stemstack":35,
  "stemlength":90,
  "stemangle":-6,
  "spacers":30,
  "bbsaddle":700,
    "saddlelength":275,
  "saddlerailstop":40,
  "saddlerailfront":130,
  "saddleraillength":60,
  "saddleheight":-1,
  "bbsetback":9,
    "hbreach":70,
  "hbdrop":125,
  "display":false
 },
 {"key":59,
 "model":"Granfondo GF02 P",
  "brand":"BMC",
  "size": 51,
  "seattube": 475,
  "toptube": 527,
  "headtube": 143,
  "headangle": 71.5,
  "seatangle": 73.5,
  "bbdrop": 71,
  "chainstay": 412,
  "wheelbase": 982,
  "stack": 546,
  "reach": 365,
  "stemstack":35,
  "stemlength":90,
  "stemangle":-6,
  "spacers":30,
  "bbsaddle":700,
    "saddlelength":275,
  "saddlerailstop":40,
  "saddlerailfront":130,
  "saddleraillength":60,
  "saddleheight":-1,
  "bbsetback":9,
    "hbreach":70,
  "hbdrop":125,
  "display":false
 },
 {"key":60,
 "model":"Synapse P",
  "brand":"Cannondale",
  "size": 51,
  "seattube": 475,
  "toptube": 524,
  "headtube": 146,
  "headangle": 71.3,
  "seatangle": 74.3,
  "bbdrop": 74,
  "chainstay": 410,
  "wheelbase": 986,
  "stack": 549,
  "reach": 370,
  "stemstack":35,
  "stemlength":90,
  "stemangle":-6,
  "spacers":30,
  "bbsaddle":700,
    "saddlelength":275,
  "saddlerailstop":40,
  "saddlerailfront":130,
  "saddleraillength":60,
  "saddleheight":-1,
  "bbsetback":9,
    "hbreach":70,
  "hbdrop":125,
  "display":false
 }
 ,
 {"key":61,
 "model":"KOOZER GX5300",
  "brand":"Advanced Mountain",
  "size": 48,
  "seattube": 480,
  "toptube": 507,
  "headtube": 100,
  "headangle": 70,
  "seatangle": 74,
  "bbdrop": 68,
  "chainstay": 435,
  "wheelbase": 999,
  "stack": 530,
  "reach": 360,
  "stemstack":35,
  "stemlength":90,
  "stemangle":-6,
  "spacers":30,
  "bbsaddle":700,
    "saddlelength":275,
  "saddlerailstop":40,
  "saddlerailfront":130,
  "saddleraillength":60,
  "saddleheight":-1,
  "bbsetback":9,
    "hbreach":70,
  "hbdrop":125,
  "display":true
 }
 ,
 {"key":62,
 "model":"KOOZER GX5300",
  "brand":"Advanced Mountain",
  "size": 50,
  "seattube": 500,
  "toptube": 512,
  "headtube": 100,
  "headangle": 70,
  "seatangle": 74,
  "bbdrop": 68,
  "chainstay": 435,
  "wheelbase": 999,
  "stack": 540,
  "reach": 364,
  "stemstack":35,
  "stemlength":90,
  "stemangle":-6,
  "spacers":30,
  "bbsaddle":700,
    "saddlelength":275,
  "saddlerailstop":40,
  "saddlerailfront":130,
  "saddleraillength":60,
  "saddleheight":-1,
  "bbsetback":9,
    "hbreach":70,
  "hbdrop":125,
  "display":false
 }
 ,
 {"key":63,
 "model":"Seaboard GR02",
  "brand":"Tsunami",
  "size": 47,
  "seattube": 470,
  "toptube": 521,
  "headtube": 130,
  "headangle": 71.5,
  "seatangle": 74.5,
  "bbdrop": 70,
  "chainstay": 425,
  "wheelbase": 996,
  "stack": 546,
  "reach": 370,
  "stemstack":35,
  "stemlength":90,
  "stemangle":-6,
  "spacers":30,
  "bbsaddle":700,
    "saddlelength":275,
  "saddlerailstop":40,
  "saddlerailfront":130,
  "saddleraillength":60,
  "saddleheight":-1,
  "bbsetback":9,
    "hbreach":70,
  "hbdrop":125,
  "display":true
 },
 {"key":64,
 "model":"Seaboard GR02",
  "brand":"Tsunami",
  "size": 50,
  "seattube": 500,
  "toptube": 529,
  "headtube": 145,
  "headangle": 72,
  "seatangle": 74.5,
  "bbdrop": 70,
  "chainstay": 425,
  "wheelbase": 999.5,
  "stack": 562.5,
  "reach": 373,
  "stemstack":35,
  "stemlength":90,
  "stemangle":-6,
  "spacers":30,
  "bbsaddle":700,
    "saddlelength":275,
  "saddlerailstop":40,
  "saddlerailfront":130,
  "saddleraillength":60,
  "saddleheight":-1,
  "bbsetback":9,
    "hbreach":70,
  "hbdrop":125,
  "display":true
 },
 {"key":65,
 "model":"Seaboard CX07",
  "brand":"Tsunami",
  "size": 47,
  "seattube": 470,
  "toptube": 522,
  "headtube": 120,
  "headangle": 71.5,
  "seatangle": 74.5,
  "bbdrop": 68,
  "chainstay": 425,
  "wheelbase": 997.2,
  "stack": 546.8,
  "reach": 370,
  "stemstack":35,
  "stemlength":90,
  "stemangle":-6,
  "spacers":30,
  "bbsaddle":700,
    "saddlelength":275,
  "saddlerailstop":40,
  "saddlerailfront":130,
  "saddleraillength":60,
  "saddleheight":-1,
  "bbsetback":9,
    "hbreach":70,
  "hbdrop":125,
  "display":true
 },
 {"key":66,
 "model":"Seaboard CX07",
  "brand":"Tsunami",
  "size": 50,
  "seattube": 500,
  "toptube": 530,
  "headtube": 140,
  "headangle": 72,
  "seatangle": 74.5,
  "bbdrop": 68,
  "chainstay": 425,
  "wheelbase": 1004.2,
  "stack": 567.7,
  "reach": 375,
  "stemstack":35,
  "stemlength":90,
  "stemangle":-6,
  "spacers":30,
  "bbsaddle":700,
    "saddlelength":275,
  "saddlerailstop":40,
  "saddlerailfront":130,
  "saddleraillength":60,
  "saddleheight":-1,
  "bbsetback":9,
    "hbreach":70,
  "hbdrop":125,
  "display":true
 }
 
]